fastapi_amis_admin_offline/__init__.py
fastapi_amis_admin_offline/static/history.min.js
fastapi_amis_admin_offline/static/vue.min.js
fastapi_amis_admin_offline/static/amis/ang-ie11.css
fastapi_amis_admin_offline/static/amis/ang.css
fastapi_amis_admin_offline/static/amis/antd-ie11.css
fastapi_amis_admin_offline/static/amis/antd.css
fastapi_amis_admin_offline/static/amis/barcode.js
fastapi_amis_admin_offline/static/amis/charts.js
fastapi_amis_admin_offline/static/amis/codemirror.js
fastapi_amis_admin_offline/static/amis/color-picker.js
fastapi_amis_admin_offline/static/amis/cropperjs.js
fastapi_amis_admin_offline/static/amis/cxd-ie11.css
fastapi_amis_admin_offline/static/amis/cxd.css
fastapi_amis_admin_offline/static/amis/dark-ie11.css
fastapi_amis_admin_offline/static/amis/dark.css
fastapi_amis_admin_offline/static/amis/exceljs.js
fastapi_amis_admin_offline/static/amis/helper.css
fastapi_amis_admin_offline/static/amis/iconfont.css
fastapi_amis_admin_offline/static/amis/iconfont.eot
fastapi_amis_admin_offline/static/amis/iconfont.svg
fastapi_amis_admin_offline/static/amis/iconfont.ttf
fastapi_amis_admin_offline/static/amis/iconfont.woff
fastapi_amis_admin_offline/static/amis/ie11-patch.css
fastapi_amis_admin_offline/static/amis/markdown.js
fastapi_amis_admin_offline/static/amis/papaparse.js
fastapi_amis_admin_offline/static/amis/rest.js
fastapi_amis_admin_offline/static/amis/rich-text.js
fastapi_amis_admin_offline/static/amis/sdk-ie11.css
fastapi_amis_admin_offline/static/amis/sdk.css
fastapi_amis_admin_offline/static/amis/sdk.js
fastapi_amis_admin_offline/static/amis/tinymce.js
fastapi_amis_admin_offline/static/amis/locale/de-DE.js
fastapi_amis_admin_offline/static/amis/thirds/@fortawesome/fontawesome-free/webfonts/fa-brands-400.ttf
fastapi_amis_admin_offline/static/amis/thirds/@fortawesome/fontawesome-free/webfonts/fa-brands-400.woff2
fastapi_amis_admin_offline/static/amis/thirds/@fortawesome/fontawesome-free/webfonts/fa-regular-400.ttf
fastapi_amis_admin_offline-0.1.0.dist-info/METADATA
fastapi_amis_admin_offline-0.1.0.dist-info/WHEEL
fastapi_amis_admin_offline-0.1.0.dist-info/top_level.txt
fastapi_amis_admin_offline-0.1.0.dist-info/RECORD
