Metadata-Version: 2.1
Name: fastapi-amis-admin-offline
Version: 0.1.0
Summary: make fastapi & amis-admin work offline without CDN
Home-page: https://github.com/love4odoo/fastapi-amis-admin-offline
Author: liunux
Author-email: liunux@qq.com
Requires-Python: >=3.6
Requires-Dist: fastapi
